dicedb_py/__init__.py
dicedb_py/command/__init__.py
dicedb_py/command/command.py
dicedb_py/command/executor.py
dicedb_py/connection/__init__.py
dicedb_py/connection/client.py
dicedb_py/connection/connect.py
dicedb_py/connection/pool.py
dicedb_py/dice.py
dicedb_py/utils/__init__.py
dicedb_py/utils/to_resp.py
dicedb_py-0.0.2.dist-info/METADATA
dicedb_py-0.0.2.dist-info/WHEEL
dicedb_py-0.0.2.dist-info/RECORD
