Metadata-Version: 2.1
Name: dicedb-py
Version: 0.0.2
Summary: Python Client for DiceDB
Home-page: https://priyanshu-panwar.github.io/dice-py
License: MIT
Keywords: dice,dice-py,dice-db,dicedb,python,client
Author: Priyanshu Panwar
Author-email: priyanshu009ch@gmail.com
Requires-Python: >=3.9,<4.0
Classifier: License :: OSI Approved :: MIT License
Classifier: Programming Language :: Python :: 3
Classifier: Programming Language :: Python :: 3.9
Classifier: Programming Language :: Python :: 3.10
Classifier: Programming Language :: Python :: 3.11
Classifier: Programming Language :: Python :: 3.12
Classifier: Programming Language :: Python :: 3.13
Classifier: Programming Language :: Python :: 3 :: Only
Classifier: Programming Language :: Python :: 3.7
Classifier: Programming Language :: Python :: 3.8
Project-URL: Repository, https://github.com/priyanshu-panwar/dice-py
